Workbook

Sheet Sales
A1: OrderID | B1: OrderDate | C1: SalespersonID | D1: ProductID | E1: Channel | F1: Region | G1: Country | H1: Quantity | I1: UnitPrice | J1: UnitCost | K1: Discount | L1: Revenue | M1: Commission | N1: Profit | O1: ProfitMargin
A2: ORD-10001 | B2: 45619 | C2: S-02 | D2: P-101 | E2: Partner | F2: =_xlfn.XLOOKUP(C2,Salespeople!$A$2:$A$11,Salespeople!$C$2:$C$11) -> EMEA | G2: =_xlfn.XLOOKUP(C2,Salespeople!$A$2:$A$11,Salespeople!$D$2:$D$11) -> Portugal | H2: 9 | I2: =_xlfn.XLOOKUP($D2,Products!$A$2:$A$16,Products!$D$2:$D$16) -> 25 | J2: =_xlfn.XLOOKUP(Sales!$D2,Products!$A$2:$A$16,Products!$E$2:$E$16) -> 11 | K2: {=_xlfn.IFS(H2<=5,0%,H2<=10,5%,H2<=15,10%,H2<=20,15%,H2>20,20%)} -> 0.05 | L2: =H2*I2*(1-K2) -> 213.75 | M2: {=L2*_xlfn.IFS(L2<=5000,0.02,L2<=15000,0.04,L2>15000,0.06)} -> 4.275 | N2: =L2-(H2*J2) -> 114.75 | O2: =N2/L2 -> 0.53684211
A3: ORD-10002 | B3: 45406 | C3: S-03 | D3: P-402 | E3: Online | F3: =_xlfn.XLOOKUP(C3,Salespeople!$A$2:$A$11,Salespeople!$C$2:$C$11) -> APAC | G3: =_xlfn.XLOOKUP(C3,Salespeople!$A$2:$A$11,Salespeople!$D$2:$D$11) -> Singapore | H3: 22 | I3: =_xlfn.XLOOKUP($D3,Products!$A$2:$A$16,Products!$D$2:$D$16) -> 95 | J3: =_xlfn.XLOOKUP(Sales!$D3,Products!$A$2:$A$16,Products!$E$2:$E$16) -> 44 | K3: {=_xlfn.IFS(H3<=5,0%,H3<=10,5%,H3<=15,10%,H3<=20,15%,H3>20,20%)} -> 0.2 | L3: =H3*I3*(1-K3) -> 1672 | M3: {=L3*_xlfn.IFS(L3<=5000,0.02,L3<=15000,0.04,L3>15000,0.06)} -> 33.44 | N3: =L3-(H3*J3) -> 704 | O3: =N3/L3 -> 0.42105263
A4: ORD-10003 | B4: 45594 | C4: S-07 | D4: P-101 | E4: Online | F4: =_xlfn.XLOOKUP(C4,Salespeople!$A$2:$A$11,Salespeople!$C$2:$C$11) -> EMEA | G4: =_xlfn.XLOOKUP(C4,Salespeople!$A$2:$A$11,Salespeople!$D$2:$D$11) -> Kenya | H4: 3 | I4: =_xlfn.XLOOKUP($D4,Products!$A$2:$A$16,Products!$D$2:$D$16) -> 25 | J4: =_xlfn.XLOOKUP(Sales!$D4,Products!$A$2:$A$16,Products!$E$2:$E$16) -> 11 | K4: {=_xlfn.IFS(H4<=5,0%,H4<=10,5%,H4<=15,10%,H4<=20,15%,H4>20,20%)} -> 0 | L4: =H4*I4*(1-K4) -> 75 | M4: {=L4*_xlfn.IFS(L4<=5000,0.02,L4<=15000,0.04,L4>15000,0.06)} -> 1.5 | N4: =L4-(H4*J4) -> 42 | O4: =N4/L4 -> 0.56
A5: ORD-10004 | B5: 45411 | C5: S-09 | D5: P-303 | E5: Online | F5: =_xlfn.XLOOKUP(C5,Salespeople!$A$2:$A$11,Salespeople!$C$2:$C$11) -> Americas | G5: =_xlfn.XLOOKUP(C5,Salespeople!$A$2:$A$11,Salespeople!$D$2:$D$11) -> Brazil | H5: 18 | I5: =_xlfn.XLOOKUP($D5,Products!$A$2:$A$16,Products!$D$2:$D$16) -> 1050 | J5: =_xlfn.XLOOKUP(Sales!$D5,Products!$A$2:$A$16,Products!$E$2:$E$16) -> 760 | K5: {=_xlfn.IFS(H5<=5,0%,H5<=10,5%,H5<=15,10%,H5<=20,15%,H5>20,20%)} -> 0.15 | L5: =H5*I5*(1-K5) -> 16065 | M5: {=L5*_xlfn.IFS(L5<=5000,0.02,L5<=15000,0.04,L5>15000,0.06)} -> 963.9 | N5: =L5-(H5*J5) -> 2385 | O5: =N5/L5 -> 0.14845938
A6: ORD-10005 | B6: 45624 | C6: S-09 | D6: P-203 | E6: Online | F6: =_xlfn.XLOOKUP(C6,Salespeople!$A$2:$A$11,Salespeople!$C$2:$C$11) -> Americas | G6: =_xlfn.XLOOKUP(C6,Salespeople!$A$2:$A$11,Salespeople!$D$2:$D$11) -> Brazil | H6: 15 | I6: =_xlfn.XLOOKUP($D6,Products!$A$2:$A$16,Products!$D$2:$D$16) -> 180 | J6: =_xlfn.XLOOKUP(Sales!$D6,Products!$A$2:$A$16,Products!$E$2:$E$16) -> 105 | K6: {=_xlfn.IFS(H6<=5,0%,H6<=10,5%,H6<=15,10%,H6<=20,15%,H6>20,20%)} -> 0.1 | L6: =H6*I6*(1-K6) -> 2430 | M6: {=L6*_xlfn.IFS(L6<=5000,0.02,L6<=15000,0.04,L6>15000,0.06)} -> 48.6 | N6: =L6-(H6*J6) -> 855 | O6: =N6/L6 -> 0.35185185
A7: ORD-10006 | B7: 45295 | C7: S-03 | D7: P-402 | E7: Retail | F7: =_xlfn.XLOOKUP(C7,Salespeople!$A$2:$A$11,Salespeople!$C$2:$C$11) -> APAC | G7: =_xlfn.XLOOKUP(C7,Salespeople!$A$2:$A$11,Salespeople!$D$2:$D$11) -> Singapore | H7: 11 | I7: =_xlfn.XLOOKUP($D7,Products!$A$2:$A$16,Products!$D$2:$D$16) -> 95 | J7: =_xlfn.XLOOKUP(Sales!$D7,Products!$A$2:$A$16,Products!$E$2:$E$16) -> 44 | K7: {=_xlfn.IFS(H7<=5,0%,H7<=10,5%,H7<=15,10%,H7<=20,15%,H7>20,20%)} -> 0.1 | L7: =H7*I7*(1-K7) -> 940.5 | M7: {=L7*_xlfn.IFS(L7<=5000,0.02,L7<=15000,0.04,L7>15000,0.06)} -> 18.81 | N7: =L7-(H7*J7) -> 456.5 | O7: =N7/L7 -> 0.48538012
A8: ORD-10007 | B8: 45371 | C8: S-04 | D8: P-403 | E8: Retail | F8: =_xlfn.XLOOKUP(C8,Salespeople!$A$2:$A$11,Salespeople!$C$2:$C$11) -> Americas | G8: =_xlfn.XLOOKUP(C8,Salespeople!$A$2:$A$11,Salespeople!$D$2:$D$11) -> Mexico | H8: 4 | I8: =_xlfn.XLOOKUP($D8,Products!$A$2:$A$16,Products!$D$2:$D$16) -> 130 | J8: =_xlfn.XLOOKUP(Sales!$D8,Products!$A$2:$A$16,Products!$E$2:$E$16) -> 62 | K8: {=_xlfn.IFS(H8<=5,0%,H8<=10,5%,H8<=15,10%,H8<=20,15%,H8>20,20%)} -> 0 | L8: =H8*I8*(1-K8) -> 520 | M8: {=L8*_xlfn.IFS(L8<=5000,0.02,L8<=15000,0.04,L8>15000,0.06)} -> 10.4 | N8: =L8-(H8*J8) -> 272 | O8: =N8/L8 -> 0.52307692
A9: ORD-10008 | B9: 45486 | C9: S-02 | D9: P-202 | E9: Retail | F9: =_xlfn.XLOOKUP(C9,Salespeople!$A$2:$A$11,Salespeople!$C$2:$C$11) -> EMEA | G9: =_xlfn.XLOOKUP(C9,Salespeople!$A$2:$A$11,Salespeople!$D$2:$D$11) -> Portugal | H9: 20 | I9: =_xlfn.XLOOKUP($D9,Products!$A$2:$A$16,Products!$D$2:$D$16) -> 520 | J9: =_xlfn.XLOOKUP(Sales!$D9,Products!$A$2:$A$16,Products!$E$2:$E$16) -> 360 | K9: {=_xlfn.IFS(H9<=5,0%,H9<=10,5%,H9<=15,10%,H9<=20,15%,H9>20,20%)} -> 0.15 | L9: =H9*I9*(1-K9) -> 8840 | M9: {=L9*_xlfn.IFS(L9<=5000,0.02,L9<=15000,0.04,L9>15000,0.06)} -> 353.6 | N9: =L9-(H9*J9) -> 1640 | O9: =N9/L9 -> 0.18552036
A10: ORD-10009 | B10: 45314 | C10: S-08 | D10: P-302 | E10: Online | F10: =_xlfn.XLOOKUP(C10,Salespeople!$A$2:$A$11,Salespeople!$C$2:$C$11) -> APAC | G10: =_xlfn.XLOOKUP(C10,Salespeople!$A$2:$A$11,Salespeople!$D$2:$D$11) -> Japan | H10: 13 | I10: =_xlfn.XLOOKUP($D10,Products!$A$2:$A$16,Products!$D$2:$D$16) -> 1750 | J10: =_xlfn.XLOOKUP(Sales!$D10,Products!$A$2:$A$16,Products!$E$2:$E$16) -> 1300 | K10: {=_xlfn.IFS(H10<=5,0%,H10<=10,5%,H10<=15,10%,H10<=20,15%,H10>20,20%)} -> 0.1 | L10: =H10*I10*(1-K10) -> 20475 | M10: {=L10*_xlfn.IFS(L10<=5000,0.02,L10<=15000,0.04,L10>15000,0.06)} -> 1228.5 | N10: =L10-(H10*J10) -> 3575 | O10: =N10/L10 -> 0.17460317
A11: ORD-10010 | B11: 45574 | C11: S-05 | D11: P-501 | E11: Partner | F11: =_xlfn.XLOOKUP(C11,Salespeople!$A$2:$A$11,Salespeople!$C$2:$C$11) -> Americas | G11: =_xlfn.XLOOKUP(C11,Salespeople!$A$2:$A$11,Salespeople!$D$2:$D$11) -> United States | H11: 20 | I11: =_xlfn.XLOOKUP($D11,Products!$A$2:$A$16,Products!$D$2:$D$16) -> 110 | J11: =_xlfn.XLOOKUP(Sales!$D11,Products!$A$2:$A$16,Products!$E$2:$E$16) -> 55 | K11: {=_xlfn.IFS(H11<=5,0%,H11<=10,5%,H11<=15,10%,H11<=20,15%,H11>20,20%)} -> 0.15 | L11: =H11*I11*(1-K11) -> 1870 | M11: {=L11*_xlfn.IFS(L11<=5000,0.02,L11<=15000,0.04,L11>15000,0.06)} -> 37.4 | N11: =L11-(H11*J11) -> 770 | O11: =N11/L11 -> 0.41176471
A12: ORD-10011 | B12: 45587 | C12: S-04 | D12: P-402 | E12: Online | F12: =_xlfn.XLOOKUP(C12,Salespeople!$A$2:$A$11,Salespeople!$C$2:$C$11) -> Americas | G12: =_xlfn.XLOOKUP(C12,Salespeople!$A$2:$A$11,Salespeople!$D$2:$D$11) -> Mexico | H12: 2 | I12: =_xlfn.XLOOKUP($D12,Products!$A$2:$A$16,Products!$D$2:$D$16) -> 95 | J12: =_xlfn.XLOOKUP(Sales!$D12,Products!$A$2:$A$16,Products!$E$2:$E$16) -> 44 | K12: {=_xlfn.IFS(H12<=5,0%,H12<=10,5%,H12<=15,10%,H12<=20,15%,H12>20,20%)} -> 0 | L12: =H12*I12*(1-K12) -> 190 | M12: {=L12*_xlfn.IFS(L12<=5000,0.02,L12<=15000,0.04,L12>15000,0.06)} -> 3.8 | N12: =L12-(H12*J12) -> 102 | O12: =N12/L12 -> 0.53684211
A13: ORD-10012 | B13: 45440 | C13: S-02 | D13: P-501 | E13: Online | F13: =_xlfn.XLOOKUP(C13,Salespeople!$A$2:$A$11,Salespeople!$C$2:$C$11) -> EMEA | G13: =_xlfn.XLOOKUP(C13,Salespeople!$A$2:$A$11,Salespeople!$D$2:$D$11) -> Portugal | H13: 4 | I13: =_xlfn.XLOOKUP($D13,Products!$A$2:$A$16,Products!$D$2:$D$16) -> 110 | J13: =_xlfn.XLOOKUP(Sales!$D13,Products!$A$2:$A$16,Products!$E$2:$E$16) -> 55 | K13: {=_xlfn.IFS(H13<=5,0%,H13<=10,5%,H13<=15,10%,H13<=20,15%,H13>20,20%)} -> 0 | L13: =H13*I13*(1-K13) -> 440 | M13: {=L13*_xlfn.IFS(L13<=5000,0.02,L13<=15000,0.04,L13>15000,0.06)} -> 8.8 | N13: =L13-(H13*J13) -> 220 | O13: =N13/L13 -> 0.5
... A201: ORD-10200 | B201: 45342 | C201: S-02 | D201: P-301 | E201: Online | F201: =_xlfn.XLOOKUP(C201,Salespeople!$A$2:$A$11,Salespeople!$C$2:$C$11) -> EMEA | G201: =_xlfn.XLOOKUP(C201,Salespeople!$A$2:$A$11,Salespeople!$D$2:$D$11) -> Portugal | H201: 23 | I201: =_xlfn.XLOOKUP($D201,Products!$A$2:$A$16,Products!$D$2:$D$16) -> 1150 | J201: =_xlfn.XLOOKUP(Sales!$D201,Products!$A$2:$A$16,Products!$E$2:$E$16) -> 820 | K201: {=_xlfn.IFS(H201<=5,0%,H201<=10,5%,H201<=15,10%,H201<=20,15%,H201>20,20%)} -> 0.2 | L201: =H201*I201*(1-K201) -> 21160 | M201: {=L201*_xlfn.IFS(L201<=5000,0.02,L201<=15000,0.04,L201>15000,0.06)} -> 1269.6 | N201: =L201-(H201*J201) -> 2300 | O201: =N201/L201 -> 0.10869565

Sheet 01_sales
A1: OrderID | B1: OrderDate | C1: SalespersonID | D1: ProductID | E1: Channel | F1: Region | G1: Country | H1: Quantity | I1: UnitPrice | J1: UnitCost | K1: Discount | L1: Revenue | M1: Commission | N1: Profit | O1: ProfitMargin
A2: ORD-10001 | B2: 45619 | C2: S-02 | D2: P-101 | E2: Partner | F2: =_xlfn.XLOOKUP(C2,Salespeople!$A$2:$A$11,Salespeople!$C$2:$C$11) -> EMEA | G2: =_xlfn.XLOOKUP(C2,Salespeople!$A$2:$A$11,Salespeople!$D$2:$D$11) -> Portugal | H2: 9 | I2: =_xlfn.XLOOKUP($D2,Products!$A$2:$A$16,Products!$D$2:$D$16) -> 25 | J2: =_xlfn.XLOOKUP(Sales!$D2,Products!$A$2:$A$16,Products!$E$2:$E$16) -> 11 | K2: {=_xlfn.IFS(H2<=5,0%,H2<=10,5%,H2<=15,10%,H2<=20,15%,H2>20,20%)} -> 0.05 | L2: =H2*I2*(1-K2) -> 213.75 | M2: {=L2*_xlfn.IFS(L2<=5000,0.02,L2<=15000,0.04,L2>15000,0.06)} -> 4.275 | N2: =L2-(H2*J2) -> 114.75 | O2: =N2/L2 -> 0.53684211
A3: ORD-10002 | B3: 45406 | C3: S-03 | D3: P-402 | E3: Online | F3: =_xlfn.XLOOKUP(C3,Salespeople!$A$2:$A$11,Salespeople!$C$2:$C$11) -> APAC | G3: =_xlfn.XLOOKUP(C3,Salespeople!$A$2:$A$11,Salespeople!$D$2:$D$11) -> Singapore | H3: 22 | I3: =_xlfn.XLOOKUP($D3,Products!$A$2:$A$16,Products!$D$2:$D$16) -> 95 | J3: =_xlfn.XLOOKUP(Sales!$D3,Products!$A$2:$A$16,Products!$E$2:$E$16) -> 44 | K3: {=_xlfn.IFS(H3<=5,0%,H3<=10,5%,H3<=15,10%,H3<=20,15%,H3>20,20%)} -> 0.2 | L3: =H3*I3*(1-K3) -> 1672 | M3: {=L3*_xlfn.IFS(L3<=5000,0.02,L3<=15000,0.04,L3>15000,0.06)} -> 33.44 | N3: =L3-(H3*J3) -> 704 | O3: =N3/L3 -> 0.42105263
A4: ORD-10003 | B4: 45594 | C4: S-07 | D4: P-101 | E4: Online | F4: =_xlfn.XLOOKUP(C4,Salespeople!$A$2:$A$11,Salespeople!$C$2:$C$11) -> EMEA | G4: =_xlfn.XLOOKUP(C4,Salespeople!$A$2:$A$11,Salespeople!$D$2:$D$11) -> Kenya | H4: 3 | I4: =_xlfn.XLOOKUP($D4,Products!$A$2:$A$16,Products!$D$2:$D$16) -> 25 | J4: =_xlfn.XLOOKUP(Sales!$D4,Products!$A$2:$A$16,Products!$E$2:$E$16) -> 11 | K4: {=_xlfn.IFS(H4<=5,0%,H4<=10,5%,H4<=15,10%,H4<=20,15%,H4>20,20%)} -> 0 | L4: =H4*I4*(1-K4) -> 75 | M4: {=L4*_xlfn.IFS(L4<=5000,0.02,L4<=15000,0.04,L4>15000,0.06)} -> 1.5 | N4: =L4-(H4*J4) -> 42 | O4: =N4/L4 -> 0.56
A5: ORD-10004 | B5: 45411 | C5: S-09 | D5: P-303 | E5: Online | F5: =_xlfn.XLOOKUP(C5,Salespeople!$A$2:$A$11,Salespeople!$C$2:$C$11) -> Americas | G5: =_xlfn.XLOOKUP(C5,Salespeople!$A$2:$A$11,Salespeople!$D$2:$D$11) -> Brazil | H5: 18 | I5: =_xlfn.XLOOKUP($D5,Products!$A$2:$A$16,Products!$D$2:$D$16) -> 1050 | J5: =_xlfn.XLOOKUP(Sales!$D5,Products!$A$2:$A$16,Products!$E$2:$E$16) -> 760 | K5: {=_xlfn.IFS(H5<=5,0%,H5<=10,5%,H5<=15,10%,H5<=20,15%,H5>20,20%)} -> 0.15 | L5: =H5*I5*(1-K5) -> 16065 | M5: {=L5*_xlfn.IFS(L5<=5000,0.02,L5<=15000,0.04,L5>15000,0.06)} -> 963.9 | N5: =L5-(H5*J5) -> 2385 | O5: =N5/L5 -> 0.14845938
A6: ORD-10005 | B6: 45624 | C6: S-09 | D6: P-203 | E6: Online | F6: =_xlfn.XLOOKUP(C6,Salespeople!$A$2:$A$11,Salespeople!$C$2:$C$11) -> Americas | G6: =_xlfn.XLOOKUP(C6,Salespeople!$A$2:$A$11,Salespeople!$D$2:$D$11) -> Brazil | H6: 15 | I6: =_xlfn.XLOOKUP($D6,Products!$A$2:$A$16,Products!$D$2:$D$16) -> 180 | J6: =_xlfn.XLOOKUP(Sales!$D6,Products!$A$2:$A$16,Products!$E$2:$E$16) -> 105 | K6: {=_xlfn.IFS(H6<=5,0%,H6<=10,5%,H6<=15,10%,H6<=20,15%,H6>20,20%)} -> 0.1 | L6: =H6*I6*(1-K6) -> 2430 | M6: {=L6*_xlfn.IFS(L6<=5000,0.02,L6<=15000,0.04,L6>15000,0.06)} -> 48.6 | N6: =L6-(H6*J6) -> 855 | O6: =N6/L6 -> 0.35185185
A7: ORD-10006 | B7: 45295 | C7: S-03 | D7: P-402 | E7: Retail | F7: =_xlfn.XLOOKUP(C7,Salespeople!$A$2:$A$11,Salespeople!$C$2:$C$11) -> APAC | G7: =_xlfn.XLOOKUP(C7,Salespeople!$A$2:$A$11,Salespeople!$D$2:$D$11) -> Singapore | H7: 11 | I7: =_xlfn.XLOOKUP($D7,Products!$A$2:$A$16,Products!$D$2:$D$16) -> 95 | J7: =_xlfn.XLOOKUP(Sales!$D7,Products!$A$2:$A$16,Products!$E$2:$E$16) -> 44 | K7: {=_xlfn.IFS(H7<=5,0%,H7<=10,5%,H7<=15,10%,H7<=20,15%,H7>20,20%)} -> 0.1 | L7: =H7*I7*(1-K7) -> 940.5 | M7: {=L7*_xlfn.IFS(L7<=5000,0.02,L7<=15000,0.04,L7>15000,0.06)} -> 18.81 | N7: =L7-(H7*J7) -> 456.5 | O7: =N7/L7 -> 0.48538012
A8: ORD-10007 | B8: 45371 | C8: S-04 | D8: P-403 | E8: Retail | F8: =_xlfn.XLOOKUP(C8,Salespeople!$A$2:$A$11,Salespeople!$C$2:$C$11) -> Americas | G8: =_xlfn.XLOOKUP(C8,Salespeople!$A$2:$A$11,Salespeople!$D$2:$D$11) -> Mexico | H8: 4 | I8: =_xlfn.XLOOKUP($D8,Products!$A$2:$A$16,Products!$D$2:$D$16) -> 130 | J8: =_xlfn.XLOOKUP(Sales!$D8,Products!$A$2:$A$16,Products!$E$2:$E$16) -> 62 | K8: {=_xlfn.IFS(H8<=5,0%,H8<=10,5%,H8<=15,10%,H8<=20,15%,H8>20,20%)} -> 0 | L8: =H8*I8*(1-K8) -> 520 | M8: {=L8*_xlfn.IFS(L8<=5000,0.02,L8<=15000,0.04,L8>15000,0.06)} -> 10.4 | N8: =L8-(H8*J8) -> 272 | O8: =N8/L8 -> 0.52307692
A9: ORD-10008 | B9: 45486 | C9: S-02 | D9: P-202 | E9: Retail | F9: =_xlfn.XLOOKUP(C9,Salespeople!$A$2:$A$11,Salespeople!$C$2:$C$11) -> EMEA | G9: =_xlfn.XLOOKUP(C9,Salespeople!$A$2:$A$11,Salespeople!$D$2:$D$11) -> Portugal | H9: 20 | I9: =_xlfn.XLOOKUP($D9,Products!$A$2:$A$16,Products!$D$2:$D$16) -> 520 | J9: =_xlfn.XLOOKUP(Sales!$D9,Products!$A$2:$A$16,Products!$E$2:$E$16) -> 360 | K9: {=_xlfn.IFS(H9<=5,0%,H9<=10,5%,H9<=15,10%,H9<=20,15%,H9>20,20%)} -> 0.15 | L9: =H9*I9*(1-K9) -> 8840 | M9: {=L9*_xlfn.IFS(L9<=5000,0.02,L9<=15000,0.04,L9>15000,0.06)} -> 353.6 | N9: =L9-(H9*J9) -> 1640 | O9: =N9/L9 -> 0.18552036
A10: ORD-10009 | B10: 45314 | C10: S-08 | D10: P-302 | E10: Online | F10: =_xlfn.XLOOKUP(C10,Salespeople!$A$2:$A$11,Salespeople!$C$2:$C$11) -> APAC | G10: =_xlfn.XLOOKUP(C10,Salespeople!$A$2:$A$11,Salespeople!$D$2:$D$11) -> Japan | H10: 13 | I10: =_xlfn.XLOOKUP($D10,Products!$A$2:$A$16,Products!$D$2:$D$16) -> 1750 | J10: =_xlfn.XLOOKUP(Sales!$D10,Products!$A$2:$A$16,Products!$E$2:$E$16) -> 1300 | K10: {=_xlfn.IFS(H10<=5,0%,H10<=10,5%,H10<=15,10%,H10<=20,15%,H10>20,20%)} -> 0.1 | L10: =H10*I10*(1-K10) -> 20475 | M10: {=L10*_xlfn.IFS(L10<=5000,0.02,L10<=15000,0.04,L10>15000,0.06)} -> 1228.5 | N10: =L10-(H10*J10) -> 3575 | O10: =N10/L10 -> 0.17460317
A11: ORD-10010 | B11: 45574 | C11: S-05 | D11: P-501 | E11: Partner | F11: =_xlfn.XLOOKUP(C11,Salespeople!$A$2:$A$11,Salespeople!$C$2:$C$11) -> Americas | G11: =_xlfn.XLOOKUP(C11,Salespeople!$A$2:$A$11,Salespeople!$D$2:$D$11) -> United States | H11: 20 | I11: =_xlfn.XLOOKUP($D11,Products!$A$2:$A$16,Products!$D$2:$D$16) -> 110 | J11: =_xlfn.XLOOKUP(Sales!$D11,Products!$A$2:$A$16,Products!$E$2:$E$16) -> 55 | K11: {=_xlfn.IFS(H11<=5,0%,H11<=10,5%,H11<=15,10%,H11<=20,15%,H11>20,20%)} -> 0.15 | L11: =H11*I11*(1-K11) -> 1870 | M11: {=L11*_xlfn.IFS(L11<=5000,0.02,L11<=15000,0.04,L11>15000,0.06)} -> 37.4 | N11: =L11-(H11*J11) -> 770 | O11: =N11/L11 -> 0.41176471
A12: ORD-10011 | B12: 45587 | C12: S-04 | D12: P-402 | E12: Online | F12: =_xlfn.XLOOKUP(C12,Salespeople!$A$2:$A$11,Salespeople!$C$2:$C$11) -> Americas | G12: =_xlfn.XLOOKUP(C12,Salespeople!$A$2:$A$11,Salespeople!$D$2:$D$11) -> Mexico | H12: 2 | I12: =_xlfn.XLOOKUP($D12,Products!$A$2:$A$16,Products!$D$2:$D$16) -> 95 | J12: =_xlfn.XLOOKUP(Sales!$D12,Products!$A$2:$A$16,Products!$E$2:$E$16) -> 44 | K12: {=_xlfn.IFS(H12<=5,0%,H12<=10,5%,H12<=15,10%,H12<=20,15%,H12>20,20%)} -> 0 | L12: =H12*I12*(1-K12) -> 190 | M12: {=L12*_xlfn.IFS(L12<=5000,0.02,L12<=15000,0.04,L12>15000,0.06)} -> 3.8 | N12: =L12-(H12*J12) -> 102 | O12: =N12/L12 -> 0.53684211
A13: ORD-10012 | B13: 45440 | C13: S-02 | D13: P-501 | E13: Online | F13: =_xlfn.XLOOKUP(C13,Salespeople!$A$2:$A$11,Salespeople!$C$2:$C$11) -> EMEA | G13: =_xlfn.XLOOKUP(C13,Salespeople!$A$2:$A$11,Salespeople!$D$2:$D$11) -> Portugal | H13: 4 | I13: =_xlfn.XLOOKUP($D13,Products!$A$2:$A$16,Products!$D$2:$D$16) -> 110 | J13: =_xlfn.XLOOKUP(Sales!$D13,Products!$A$2:$A$16,Products!$E$2:$E$16) -> 55 | K13: {=_xlfn.IFS(H13<=5,0%,H13<=10,5%,H13<=15,10%,H13<=20,15%,H13>20,20%)} -> 0 | L13: =H13*I13*(1-K13) -> 440 | M13: {=L13*_xlfn.IFS(L13<=5000,0.02,L13<=15000,0.04,L13>15000,0.06)} -> 8.8 | N13: =L13-(H13*J13) -> 220 | O13: =N13/L13 -> 0.5
... A201: ORD-10200 | B201: 45342 | C201: S-02 | D201: P-301 | E201: Online | F201: =_xlfn.XLOOKUP(C201,Salespeople!$A$2:$A$11,Salespeople!$C$2:$C$11) -> EMEA | G201: =_xlfn.XLOOKUP(C201,Salespeople!$A$2:$A$11,Salespeople!$D$2:$D$11) -> Portugal | H201: 23 | I201: =_xlfn.XLOOKUP($D201,Products!$A$2:$A$16,Products!$D$2:$D$16) -> 1150 | J201: =_xlfn.XLOOKUP(Sales!$D201,Products!$A$2:$A$16,Products!$E$2:$E$16) -> 820 | K201: {=_xlfn.IFS(H201<=5,0%,H201<=10,5%,H201<=15,10%,H201<=20,15%,H201>20,20%)} -> 0.2 | L201: =H201*I201*(1-K201) -> 21160 | M201: {=L201*_xlfn.IFS(L201<=5000,0.02,L201<=15000,0.04,L201>15000,0.06)} -> 1269.6 | N201: =L201-(H201*J201) -> 2300 | O201: =N201/L201 -> 0.10869565
L202: =SUM(L2:L201) -> 1058838.6

Sheet Products
A1: ProductID | B1: Product | C1: Category | D1: UnitPrice | E1: UnitCost
A2: P-101 | B2: Wireless Mouse | C2: Accessories | D2: 25 | E2: 11
A3: P-102 | B3: Mechanical Keyboard | C3: Accessories | D3: 79 | E3: 38
A4: P-103 | B4: USB-C Hub | C4: Accessories | D4: 45 | E4: 19
A5: P-104 | B5: Laptop Stand | C5: Accessories | D5: 35 | E5: 14
A6: P-201 | B6: 27in Monitor | C6: Displays | D6: 240 | E6: 150
A7: P-202 | B7: 34in Ultrawide | C7: Displays | D7: 520 | E7: 360
A8: P-203 | B8: Portable Monitor | C8: Displays | D8: 180 | E8: 105
A9: P-301 | B9: Ultrabook 14 | C9: Laptops | D9: 1150 | E9: 820
A10: P-302 | B10: Gaming Laptop 16 | C10: Laptops | D10: 1750 | E10: 1300
A11: P-303 | B11: Business Laptop 15 | C11: Laptops | D11: 1050 | E11: 760
A12: P-401 | B12: Noise-Cancel Headset | C12: Audio | D12: 210 | E12: 120
A13: P-402 | B13: Desk Speakers | C13: Audio | D13: 95 | E13: 44
... A16: P-502 | B16: Document Scanner | C16: Peripherals | D16: 160 | E16: 88

Sheet 01_products
A1: ProductID | B1: Product | C1: Category | D1: UnitPrice | E1: UnitCost
A2: P-101 | B2: Wireless Mouse | C2: Accessories | D2: 25 | E2: 11
A3: P-102 | B3: Mechanical Keyboard | C3: Accessories | D3: 79 | E3: 38
A4: P-103 | B4: USB-C Hub | C4: Accessories | D4: 45 | E4: 19
A5: P-104 | B5: Laptop Stand | C5: Accessories | D5: 35 | E5: 14
A6: P-201 | B6: 27in Monitor | C6: Displays | D6: 240 | E6: 150
A7: P-202 | B7: 34in Ultrawide | C7: Displays | D7: 520 | E7: 360
A8: P-203 | B8: Portable Monitor | C8: Displays | D8: 180 | E8: 105
A9: P-301 | B9: Ultrabook 14 | C9: Laptops | D9: 1150 | E9: 820
A10: P-302 | B10: Gaming Laptop 16 | C10: Laptops | D10: 1750 | E10: 1300
A11: P-303 | B11: Business Laptop 15 | C11: Laptops | D11: 1050 | E11: 760
A12: P-401 | B12: Noise-Cancel Headset | C12: Audio | D12: 210 | E12: 120
A13: P-402 | B13: Desk Speakers | C13: Audio | D13: 95 | E13: 44
... A16: P-502 | B16: Document Scanner | C16: Peripherals | D16: 160 | E16: 88

Sheet 01_salespeople
A1: SalespersonID | B1: Salesperson | C1: Region | D1: Country
A2: S-01 | B2: Aisha Khan | C2: EMEA | D2: United Kingdom
A3: S-02 | B3: Bruno Costa | C3: EMEA | D3: Portugal
A4: S-03 | B4: Chen Wei | C4: APAC | D4: Singapore
A5: S-04 | B5: Diana Lopez | C5: Americas | D5: Mexico
A6: S-05 | B6: Ethan Brooks | C6: Americas | D6: United States
A7: S-06 | B7: Fatima Noor | C7: EMEA | D7: United Arab Emirates
A8: S-07 | B8: Grace Mwangi | C8: EMEA | D8: Kenya
A9: S-08 | B9: Hiro Tanaka | C9: APAC | D9: Japan
A10: S-09 | B10: Isabela Rocha | C10: Americas | D10: Brazil
A11: S-10 | B11: Jamal Edwards | C11: Americas | D11: Canada

Sheet Salespeople
A1: SalespersonID | B1: Salesperson | C1: Region | D1: Country
A2: S-01 | B2: Aisha Khan | C2: EMEA | D2: United Kingdom
A3: S-02 | B3: Bruno Costa | C3: EMEA | D3: Portugal
A4: S-03 | B4: Chen Wei | C4: APAC | D4: Singapore
A5: S-04 | B5: Diana Lopez | C5: Americas | D5: Mexico
A6: S-05 | B6: Ethan Brooks | C6: Americas | D6: United States
A7: S-06 | B7: Fatima Noor | C7: EMEA | D7: United Arab Emirates
A8: S-07 | B8: Grace Mwangi | C8: EMEA | D8: Kenya
A9: S-08 | B9: Hiro Tanaka | C9: APAC | D9: Japan
A10: S-09 | B10: Isabela Rocha | C10: Americas | D10: Brazil
A11: S-10 | B11: Jamal Edwards | C11: Americas | D11: Canada
